README.md
setup.py
alibabacloud_iot_api_gateway/__init__.py
alibabacloud_iot_api_gateway/client.py
alibabacloud_iot_api_gateway/models.py
alibabacloud_iot_api_gateway.egg-info/PKG-INFO
alibabacloud_iot_api_gateway.egg-info/SOURCES.txt
alibabacloud_iot_api_gateway.egg-info/dependency_links.txt
alibabacloud_iot_api_gateway.egg-info/requires.txt
alibabacloud_iot_api_gateway.egg-info/top_level.txt